authx/__init__.py
authx/config.py
authx/core.py
authx/dependencies.py
authx/exceptions.py
authx/main.py
authx/py.typed
authx/schema.py
authx/token.py
authx/types.py
authx/_internal/__init__.py
authx/_internal/_callback.py
authx/_internal/_error.py
authx/_internal/_logger.py
authx/_internal/_scopes.py
authx/_internal/_signature.py
authx/_internal/_utils.py
authx-1.5.0.dist-info/METADATA
authx-1.5.0.dist-info/WHEEL
authx-1.5.0.dist-info/licenses/LICENSE
authx-1.5.0.dist-info/RECORD
