Metadata-Version: 2.4
Name: authx
Version: 1.5.0
Summary: Ready to use and customizable Authentications and Oauth2 management for FastAPI
Project-URL: Homepage, https://github.com/yezz123/authx
Project-URL: Documentation, https://authx.yezz.me/
Project-URL: Funding, https://github.com/sponsors/yezz123
Project-URL: Source, https://github.com/yezz123/authx
Project-URL: Changelog, https://authx.yezz.me/release/
Author-email: Yasser Tahiri <hello@yezz.me>
License-Expression: MIT
License-File: LICENSE
Keywords: Authentication,Cookie,FastAPI,JWT,Oauth2,Pydantic
Classifier: Development Status :: 4 - Beta
Classifier: Framework :: AsyncIO
Classifier: Framework :: FastAPI
Classifier: Framework :: Pydantic
Classifier: Framework :: Pydantic :: 2
Classifier: Intended Audience :: Developers
Classifier: Intended Audience :: Information Technology
Classifier: License :: OSI Approved :: MIT License
Classifier: Operating System :: OS Independent
Classifier: Programming Language :: Python
Classifier: Programming Language :: Python :: 3
Classifier: Programming Language :: Python :: 3 :: Only
Classifier: Programming Language :: Python :: 3.9
Classifier: Programming Language :: Python :: 3.10
Classifier: Programming Language :: Python :: 3.11
Classifier: Programming Language :: Python :: 3.12
Classifier: Programming Language :: Python :: 3.13
Classifier: Programming Language :: Python :: 3.14
Classifier: Topic :: Internet
Classifier: Topic :: Internet :: WWW/HTTP :: Session
Classifier: Topic :: Software Development :: Libraries :: Python Modules
Classifier: Typing :: Typed
Requires-Python: >=3.9
Requires-Dist: fastapi>=0.111.0
Requires-Dist: itsdangerous<3.0.0,>=2.2.0
Requires-Dist: pydantic-settings>=2.1.0
Requires-Dist: pydantic<3.0.0,>=2.10.5
Requires-Dist: pyjwt[crypto]<3.0.0,>=2.6.0
Requires-Dist: python-dateutil<3.0.0,>=2.8
Requires-Dist: python-jose<4.0.0,>=3.3.0
Requires-Dist: pytz<2026.0,>=2023.3
